{"id": 1, "data": {"text": "Figura 10 - Idade, tipo de rocha e distribui\u00e7\u00e3o regional    vulcanismo mesoz\u00f3ico - cenoz\u00f3ico    Brasil.."}, "annotations": [{"id": 1, "created_username": " null, 0", "created_ago": "", "result": [{"value": {"start": "71", "end": "80", "text": "mesoz\u00f3ico", "labels": ["UNIDADE_CRONO"], "URI": "#Mesozoic"}, "id": 12, "from_name": "label", "to_name": "text", "type": "labels", "origin": "prediction"}, {"value": {"start": "83", "end": "92", "text": "cenoz\u00f3ico", "labels": ["UNIDADE_CRONO"], "URI": "#Cenozoic"}, "id": 14, "from_name": "label", "to_name": "text", "type": "labels", "origin": "prediction"}, {"from_id": "12", "to_id": "14", "type": "relation", "direction": "right", "labels": ["located_in"]}, {"from_id": "14", "to_id": "12", "type": "relation", "direction": "right", "labels": ["located_in"]}]}]}