{"id": 1, "data": {"text": "O objetivo, aqui, \u00e9 descrever conodontes mississipianos por meio de sua moderna classifica\u00e7\u00e3o sistem\u00e1tica segundo Sweet (1988), tendo em vista sua import\u00e2ncia em sequ\u00eancia carbonifera mais antiga que ocorre    area    Alto Tapaj\u00f3s e               as 1 - Universidade Federal    Rio Grande    Sul (UFRGS), Departamento de Paleontologia e Estratigrafia, Instituto de Geoci\u00eancias, Av. Bento Gon\u00e7alves, 9 500, 91509-900, Campus    Vale, Porto Alegre, RS, Brasil.."}, "annotations": [{"id": 1, "created_username": " null, 0", "created_ago": "", "result": [{"value": {"start": "41", "end": "55", "text": "mississipianos", "labels": ["UNIDADE_CRONO"], "URI": "#Mississippian"}, "id": 8, "from_name": "label", "to_name": "text", "type": "labels", "origin": "prediction"}, {"value": {"start": "172", "end": "183", "text": "carbonifera", "labels": ["UNIDADE_CRONO"], "URI": "#Carboniferous"}, "id": 29, "from_name": "label", "to_name": "text", "type": "labels", "origin": "prediction"}, {"from_id": "8", "to_id": "29", "type": "relation", "direction": "right", "labels": ["located_in"]}, {"from_id": "8", "to_id": "29", "type": "relation", "direction": "right", "labels": ["located_in"]}, {"from_id": "8", "to_id": "29", "type": "relation", "direction": "right", "labels": ["located_in"]}, {"from_id": "29", "to_id": "8", "type": "relation", "direction": "right", "labels": ["located_in"]}]}]}