{"id": 1, "data": {"text": "Tal car\u00e1ter fossilifero e bioturbado prossegue     calcilutitos e folhelhos cinzentos    Membro Taquari, acima.."}, "annotations": [{"id": 1, "created_username": " null, 0", "created_ago": "", "result": [{"value": {"start": "89", "end": "103", "text": "Membro Taquari", "labels": ["UNIDADE_LITO"], "URI": "#membro_007"}, "id": 10, "from_name": "label", "to_name": "text", "type": "labels", "origin": "prediction"}, {"value": {"start": "51", "end": "63", "text": "calcilutitos", "labels": ["ROCHA"], "URI": "#calcilutite"}, "id": 6, "from_name": "label", "to_name": "text", "type": "labels", "origin": "prediction"}, {"value": {"start": "66", "end": "75", "text": "folhelhos", "labels": ["ROCHA"], "URI": "#shale"}, "id": 8, "from_name": "label", "to_name": "text", "type": "labels", "origin": "prediction"}, {"from_id": "10", "to_id": "6", "type": "relation", "direction": "right", "labels": ["located_in"]}, {"from_id": "10", "to_id": "8", "type": "relation", "direction": "right", "labels": ["located_in"]}]}]}