{"id": 1, "data": {"text": "entanto, Frakes et al. (1992),               estudos mais recentes, propuseram um modo frio iniciado    Neojur\u00e1ssico e conclu\u00eddo    mesocret\u00e1ceo, com a transi\u00e7\u00e3o para condi\u00e7\u00f5es clim\u00e1ticas mais quentes entre o Aptiano e o Albiano.."}, "annotations": [{"id": 1, "created_username": " null, 0", "created_ago": "", "result": [{"value": {"start": "209", "end": "216", "text": "Aptiano", "labels": ["UNIDADE_CRONO"], "URI": "#Aptian"}, "id": 33, "from_name": "label", "to_name": "text", "type": "labels", "origin": "prediction"}, {"value": {"start": "221", "end": "228", "text": "Albiano", "labels": ["UNIDADE_CRONO"], "URI": "#Albian"}, "id": 36, "from_name": "label", "to_name": "text", "type": "labels", "origin": "prediction"}, {"from_id": "33", "to_id": "36", "type": "relation", "direction": "right", "labels": ["located_in"]}, {"from_id": "36", "to_id": "33", "type": "relation", "direction": "right", "labels": ["located_in"]}]}]}