{"10": ["ACRE", "BACIA DE ACRE"], "35": ["ALTO-TAPAJ\u00d3S", "BACIA DE ALTO-TAPAJ\u00d3S"], "30": ["AMAZONAS", "BACIA DE AMAZONAS"], "150": ["ARARIPE", "BACIA DE ARARIPE"], "325": ["BANANAL", "BACIA DE BANANAL"], "80": ["BARREIRINHAS", "BACIA DE BARREIRINHAS", "BARREIRINHAS MAR", "BARREIRINHAS TERRA"], "266": ["CAMAMU-ALMADA", "BACIA DE CAMAMU-ALMADA", "ALMADA MAR", "ALMADA TERRA", "CAMAMU MAR", "CAMAMU TERRA"], "281": ["CAMPOS", "BACIA DE CAMPOS", "CAMPOS MAR", "CAMPOS TERRA", "BC"], "96": ["CEAR\u00c1", "BACIA DE CEAR\u00c1"], "256": ["CUMURUXATIBA", "BACIA DE CUMURUXATIBA", "CUMURUXATIBA MAR", "CUMURUXATIBA TERRA"], "270": ["ESP\u00cdRITO SANTO", "BACIA DE ESP\u00cdRITO SANTO", "ESP\u00cdRITO SANTO MAR", "ESP\u00cdRITO SANTO TERRA"], "51": ["FOZ DO AMAZONAS", "BACIA DE FOZ DO AMAZONAS"], "200": ["IREC\u00ca", "BACIA DE IREC\u00ca"], "236": ["JACU\u00cdPE", "BACIA DE JACU\u00cdPE"], "210": ["JATOB\u00c1", "BACIA DE JATOB\u00c1"], "250": ["JEQUITINHONHA", "BACIA DE JEQUITINHONHA", "JEQUITINHONHA MAR", "JEQUITINHONHA TERRA"], "50": ["MARAJ\u00d3", "BACIA DE MARAJ\u00d3"], "261": ["MUCURI MAR", "BACIA DE MUCURI MAR"], "260": ["MUCURI TERRA", "BACIA DE MUCURI TERRA"], "315": ["PANTANAL", "BACIA DE PANTANAL"], "76": ["PAR\u00c1-MARANH\u00c3O", "BACIA DE PAR\u00c1-MARANH\u00c3O"], "300": ["PARAN\u00c1", "BACIA DE PARAN\u00c1"], "320": ["PARECIS-ALTO XINGU", "BACIA DE PARECIS-ALTO XINGU"], "90": ["PARNA\u00cdBA", "BACIA DE PARNA\u00cdBA"], "381": ["PELOTAS", "BACIA DE PELOTAS", "PELOTAS MAR", "PELOTAS TERRA"], "106": ["PERNAMBUCO-PARA\u00cdBA", "BACIA DE PERNAMBUCO-PARA\u00cdBA", "PERNAMBUCO-PARA\u00cdBA MAR", "PERNAMBUCO-PARA\u00cdBA TERRA"], "100": ["POTIGUAR", "BACIA DE POTIGUAR", "POTIGUAR MAR", "POTIGUAR TERRA"], "240": ["REC\u00d4NCAVO", "BACIA DE REC\u00d4NCAVO", "REC\u00d4NCAVO MAR", "REC\u00d4NCAVO TERRA"], "66": ["RIO DO PEIXE", "BACIA DE RIO DO PEIXE"], "316": ["SANTOS", "BACIA DE SANTOS", "BC"], "275": ["S\u00c3O FRANCISCO", "BACIA DE S\u00c3O FRANCISCO"], "70": ["S\u00c3O LUIZ", "BACIA DE S\u00c3O LUIZ", "S\u00c3O LUIS"], "116": ["SERGIPE-ALAGOAS", "BACIA DE SERGIPE-ALAGOAS", "ALAGOAS MAR", "ALAGOAS TERRA", "SERGIPE MAR", "SERGIPE TERRA"], "20": ["SOLIM\u00d5ES", "BACIA DE SOLIM\u00d5ES"], "40": ["TACUTU", "BACIA DE TACUTU"], "220": ["TUCANO CENTRAL", "BACIA DE TUCANO CENTRAL"], "215": ["TUCANO NORTE", "BACIA DE TUCANO NORTE"], "230": ["TUCANO SUL", "BACIA DE TUCANO SUL"], "15": ["MADRE DE DIOS", "BACIA DE MADRE DE DIOS"], "55": ["AMAP\u00c1", "BACIA DE AMAP\u00c1"], "60": ["BRAGANCA VIZEU", "BRAGANCA VIZEU-ILHA NOVA", "BACIA DE BRAGANCA VIZEU", "BRAGANCA-VIZEU"], "95": ["MALHADO VERMELHO", "BACIA DE MALHADO VERMELHO"], "110": ["IGUATU", "BACIA DE IGUATU"], "125": ["LIMA CAMPOS", "BACIA DE LIMA CAMPOS"], "130": ["IC\u00d3", "BACIA DE IC\u00d3"], "135": ["POMBAL", "BACIA DE POMBAL"], "140": ["SOUZA", "BACIA DE SOUZA"], "145": ["TRIUNFO", "BACIA DE TRIUNFO"], "155": ["BARRO", "BACIA DE BARRO"], "160": ["CEDRO", "BACIA DE CEDRO"], "165": ["SERRA DO IN\u00c1CIO", "BACIA DE SERRA DO IN\u00c1CIO"], "170": ["S\u00c3O JOS\u00c9 DO BELMONTE", "BACIA DE S\u00c3O JOS\u00c9 DO BELMONTE"], "180": ["MIRANDIBA", "BACIA DE MIRANDIBA"], "175": ["BOM NOME", "BACIA DE BOM NOME"], "185": ["TUPANACI", "BACIA DE TUPANACI"], "190": ["BET\u00c2NIA", "BACIA DE BET\u00c2NIA"], "195": ["AFOGADOS DA INGAZEIRA", "BACIA DE AFOGADOS DA INGAZEIRA"], "205": ["ITABERABA", "BACIA DE ITABERABA"], "285": ["ITABORA\u00cd", "BACIA DE ITABORA\u00cd"], "290": ["RESENDE", "BACIA DE RESENDE"], "295": ["TAUBAT\u00c9", "BACIA DE TAUBAT\u00c9"], "305": ["S\u00c3O PAULO", "BACIA DE S\u00c3O PAULO"], "310": ["CURITIBA", "BACIA DE CURITIBA"], "330": ["\u00c1GUA BONITA", "BACIA DE \u00c1GUA BONITA"]}